[
  {
    "name": "New India Assura",
    "path": "/company/NIACL/consolidated/",
    "slug": "NIACL",
    "ev_ebitda": "",
    "pe": "",
    "pb": "",
    "roce": "",
    "roe": "",
    "promoter_holding": "",
    "sales_growth_3y": "",
    "mkt_cap": "",
    "cmp": ""
  },
  {
    "name": "ACC",
    "path": "/company/ACC/consolidated/",
    "slug": "ACC",
    "ev_ebitda": "",
    "pe": "",
    "pb": "",
    "roce": "",
    "roe": "",
    "promoter_holding": "",
    "sales_growth_3y": "",
    "mkt_cap": "",
    "cmp": ""
  },
  {
    "name": "KIOCL",
    "path": "/company/KIOCL/",
    "slug": "KIOCL",
    "ev_ebitda": "",
    "pe": "",
    "pb": "",
    "roce": "",
    "roe": "",
    "promoter_holding": "",
    "sales_growth_3y": "",
    "mkt_cap": "",
    "cmp": ""
  },
  {
    "name": "AWL Agri Busine.",
    "path": "/company/AWL/consolidated/",
    "slug": "AWL",
    "ev_ebitda": "",
    "pe": "",
    "pb": "",
    "roce": "",
    "roe": "",
    "promoter_holding": "",
    "sales_growth_3y": "",
    "mkt_cap": "",
    "cmp": ""
  },
  {
    "name": "Force Motors",
    "path": "/company/FORCEMOT/consolidated/",
    "slug": "FORCEMOT",
    "ev_ebitda": "",
    "pe": "",
    "pb": "",
    "roce": "",
    "roe": "",
    "promoter_holding": "",
    "sales_growth_3y": "",
    "mkt_cap": "",
    "cmp": ""
  },
  {
    "name": "Tenneco Clean",
    "path": "/company/TENNIND/consolidated/",
    "slug": "TENNIND",
    "ev_ebitda": "",
    "pe": "",
    "pb": "",
    "roce": "",
    "roe": "",
    "promoter_holding": "",
    "sales_growth_3y": "",
    "mkt_cap": "",
    "cmp": ""
  },
  {
    "name": "CESC",
    "path": "/company/CESC/consolidated/",
    "slug": "CESC",
    "ev_ebitda": "",
    "pe": "",
    "pb": "",
    "roce": "",
    "roe": "",
    "promoter_holding": "",
    "sales_growth_3y": "",
    "mkt_cap": "",
    "cmp": ""
  },
  {
    "name": "Syrma SGS Tech.",
    "path": "/company/SYRMA/consolidated/",
    "slug": "SYRMA",
    "ev_ebitda": "",
    "pe": "",
    "pb": "",
    "roce": "",
    "roe": "",
    "promoter_holding": "",
    "sales_growth_3y": "",
    "mkt_cap": "",
    "cmp": ""
  },
  {
    "name": "Data Pattern",
    "path": "/company/DATAPATTNS/",
    "slug": "DATAPATTNS",
    "ev_ebitda": "",
    "pe": "",
    "pb": "",
    "roce": "",
    "roe": "",
    "promoter_holding": "",
    "sales_growth_3y": "",
    "mkt_cap": "",
    "cmp": ""
  },
  {
    "name": "Sumitomo Chemi.",
    "path": "/company/SUMICHEM/",
    "slug": "SUMICHEM",
    "ev_ebitda": "",
    "pe": "",
    "pb": "",
    "roce": "",
    "roe": "",
    "promoter_holding": "",
    "sales_growth_3y": "",
    "mkt_cap": "",
    "cmp": ""
  },
  {
    "name": "Nexus Select",
    "path": "/company/NXST/consolidated/",
    "slug": "NXST",
    "ev_ebitda": "",
    "pe": "",
    "pb": "",
    "roce": "",
    "roe": "",
    "promoter_holding": "",
    "sales_growth_3y": "",
    "mkt_cap": "",
    "cmp": ""
  },
  {
    "name": "MTAR Technologie",
    "path": "/company/MTARTECH/",
    "slug": "MTARTECH",
    "ev_ebitda": "",
    "pe": "",
    "pb": "",
    "roce": "",
    "roe": "",
    "promoter_holding": "",
    "sales_growth_3y": "",
    "mkt_cap": "",
    "cmp": ""
  },
  {
    "name": "Emmvee Photovol.",
    "path": "/company/EMMVEE/consolidated/",
    "slug": "EMMVEE",
    "ev_ebitda": "",
    "pe": "",
    "pb": "",
    "roce": "",
    "roe": "",
    "promoter_holding": "",
    "sales_growth_3y": "",
    "mkt_cap": "",
    "cmp": ""
  },
  {
    "name": "Asahi India Glas",
    "path": "/company/ASAHIINDIA/consolidated/",
    "slug": "ASAHIINDIA",
    "ev_ebitda": "",
    "pe": "",
    "pb": "",
    "roce": "",
    "roe": "",
    "promoter_holding": "",
    "sales_growth_3y": "",
    "mkt_cap": "",
    "cmp": ""
  },
  {
    "name": "Indraprastha Gas",
    "path": "/company/IGL/consolidated/",
    "slug": "IGL",
    "ev_ebitda": "",
    "pe": "",
    "pb": "",
    "roce": "",
    "roe": "",
    "promoter_holding": "",
    "sales_growth_3y": "",
    "mkt_cap": "",
    "cmp": ""
  },
  {
    "name": "Deepak Nitrite",
    "path": "/company/DEEPAKNTR/consolidated/",
    "slug": "DEEPAKNTR",
    "ev_ebitda": "",
    "pe": "",
    "pb": "",
    "roce": "",
    "roe": "",
    "promoter_holding": "",
    "sales_growth_3y": "",
    "mkt_cap": "",
    "cmp": ""
  },
  {
    "name": "Piramal Pharma",
    "path": "/company/PPLPHARMA/consolidated/",
    "slug": "PPLPHARMA",
    "ev_ebitda": "",
    "pe": "",
    "pb": "",
    "roce": "",
    "roe": "",
    "promoter_holding": "",
    "sales_growth_3y": "",
    "mkt_cap": "",
    "cmp": ""
  },
  {
    "name": "HBL Engineering",
    "path": "/company/HBLENGINE/consolidated/",
    "slug": "HBLENGINE",
    "ev_ebitda": "",
    "pe": "",
    "pb": "",
    "roce": "",
    "roe": "",
    "promoter_holding": "",
    "sales_growth_3y": "",
    "mkt_cap": "",
    "cmp": ""
  },
  {
    "name": "Kalpataru Proj.",
    "path": "/company/KPIL/consolidated/",
    "slug": "KPIL",
    "ev_ebitda": "",
    "pe": "",
    "pb": "",
    "roce": "",
    "roe": "",
    "promoter_holding": "",
    "sales_growth_3y": "",
    "mkt_cap": "",
    "cmp": ""
  },
  {
    "name": "IIFL Finance",
    "path": "/company/IIFL/consolidated/",
    "slug": "IIFL",
    "ev_ebitda": "",
    "pe": "",
    "pb": "",
    "roce": "",
    "roe": "",
    "promoter_holding": "",
    "sales_growth_3y": "",
    "mkt_cap": "",
    "cmp": ""
  },
  {
    "name": "Triveni Turbine",
    "path": "/company/TRITURBINE/consolidated/",
    "slug": "TRITURBINE",
    "ev_ebitda": "",
    "pe": "",
    "pb": "",
    "roce": "",
    "roe": "",
    "promoter_holding": "",
    "sales_growth_3y": "",
    "mkt_cap": "",
    "cmp": ""
  },
  {
    "name": "RBL Bank",
    "path": "/company/RBLBANK/",
    "slug": "RBLBANK",
    "ev_ebitda": "",
    "pe": "",
    "pb": "",
    "roce": "",
    "roe": "",
    "promoter_holding": "",
    "sales_growth_3y": "",
    "mkt_cap": "",
    "cmp": ""
  },
  {
    "name": "Grindwell Norton",
    "path": "/company/GRINDWELL/consolidated/",
    "slug": "GRINDWELL",
    "ev_ebitda": "",
    "pe": "",
    "pb": "",
    "roce": "",
    "roe": "",
    "promoter_holding": "",
    "sales_growth_3y": "",
    "mkt_cap": "",
    "cmp": ""
  },
  {
    "name": "Craftsman Auto",
    "path": "/company/CRAFTSMAN/consolidated/",
    "slug": "CRAFTSMAN",
    "ev_ebitda": "",
    "pe": "",
    "pb": "",
    "roce": "",
    "roe": "",
    "promoter_holding": "",
    "sales_growth_3y": "",
    "mkt_cap": "",
    "cmp": ""
  },
  {
    "name": "ACME Solar Hold.",
    "path": "/company/ACMESOLAR/consolidated/",
    "slug": "ACMESOLAR",
    "ev_ebitda": "",
    "pe": "",
    "pb": "",
    "roce": "",
    "roe": "",
    "promoter_holding": "",
    "sales_growth_3y": "",
    "mkt_cap": "",
    "cmp": ""
  },
  {
    "name": "Neuland Labs.",
    "path": "/company/NEULANDLAB/consolidated/",
    "slug": "NEULANDLAB",
    "ev_ebitda": "",
    "pe": "",
    "pb": "",
    "roce": "",
    "roe": "",
    "promoter_holding": "",
    "sales_growth_3y": "",
    "mkt_cap": "",
    "cmp": ""
  },
  {
    "name": "Astrazeneca Phar",
    "path": "/company/ASTRAZEN/",
    "slug": "ASTRAZEN",
    "ev_ebitda": "",
    "pe": "",
    "pb": "",
    "roce": "",
    "roe": "",
    "promoter_holding": "",
    "sales_growth_3y": "",
    "mkt_cap": "",
    "cmp": ""
  },
  {
    "name": "IFCI",
    "path": "/company/IFCI/consolidated/",
    "slug": "IFCI",
    "ev_ebitda": "",
    "pe": "",
    "pb": "",
    "roce": "",
    "roe": "",
    "promoter_holding": "",
    "sales_growth_3y": "",
    "mkt_cap": "",
    "cmp": ""
  },
  {
    "name": "Sammaan Capital",
    "path": "/company/SAMMAANCAP/consolidated/",
    "slug": "SAMMAANCAP",
    "ev_ebitda": "",
    "pe": "",
    "pb": "",
    "roce": "",
    "roe": "",
    "promoter_holding": "",
    "sales_growth_3y": "",
    "mkt_cap": "",
    "cmp": ""
  },
  {
    "name": "KPIT Technologi.",
    "path": "/company/KPITTECH/consolidated/",
    "slug": "KPITTECH",
    "ev_ebitda": "",
    "pe": "",
    "pb": "",
    "roce": "",
    "roe": "",
    "promoter_holding": "",
    "sales_growth_3y": "",
    "mkt_cap": "",
    "cmp": ""
  },
  {
    "name": "Aegis Vopak Term",
    "path": "/company/AEGISVOPAK/consolidated/",
    "slug": "AEGISVOPAK",
    "ev_ebitda": "",
    "pe": "",
    "pb": "",
    "roce": "",
    "roe": "",
    "promoter_holding": "",
    "sales_growth_3y": "",
    "mkt_cap": "",
    "cmp": ""
  },
  {
    "name": "Kaynes Tech",
    "path": "/company/KAYNES/consolidated/",
    "slug": "KAYNES",
    "ev_ebitda": "",
    "pe": "",
    "pb": "",
    "roce": "",
    "roe": "",
    "promoter_holding": "",
    "sales_growth_3y": "",
    "mkt_cap": "",
    "cmp": ""
  },
  {
    "name": "GE Shipping Co",
    "path": "/company/GESHIP/consolidated/",
    "slug": "GESHIP",
    "ev_ebitda": "",
    "pe": "",
    "pb": "",
    "roce": "",
    "roe": "",
    "promoter_holding": "",
    "sales_growth_3y": "",
    "mkt_cap": "",
    "cmp": ""
  },
  {
    "name": "G M D C",
    "path": "/company/GMDCLTD/consolidated/",
    "slug": "GMDCLTD",
    "ev_ebitda": "",
    "pe": "",
    "pb": "",
    "roce": "",
    "roe": "",
    "promoter_holding": "",
    "sales_growth_3y": "",
    "mkt_cap": "",
    "cmp": ""
  },
  {
    "name": "Affle 3i",
    "path": "/company/AFFLE/consolidated/",
    "slug": "AFFLE",
    "ev_ebitda": "",
    "pe": "",
    "pb": "",
    "roce": "",
    "roe": "",
    "promoter_holding": "",
    "sales_growth_3y": "",
    "mkt_cap": "",
    "cmp": ""
  },
  {
    "name": "The Ramco Cement",
    "path": "/company/RAMCOCEM/consolidated/",
    "slug": "RAMCOCEM",
    "ev_ebitda": "",
    "pe": "",
    "pb": "",
    "roce": "",
    "roe": "",
    "promoter_holding": "",
    "sales_growth_3y": "",
    "mkt_cap": "",
    "cmp": ""
  },
  {
    "name": "OneSource Speci.",
    "path": "/company/ONESOURCE/consolidated/",
    "slug": "ONESOURCE",
    "ev_ebitda": "",
    "pe": "",
    "pb": "",
    "roce": "",
    "roe": "",
    "promoter_holding": "",
    "sales_growth_3y": "",
    "mkt_cap": "",
    "cmp": ""
  },
  {
    "name": "TD Power Systems",
    "path": "/company/TDPOWERSYS/consolidated/",
    "slug": "TDPOWERSYS",
    "ev_ebitda": "",
    "pe": "",
    "pb": "",
    "roce": "",
    "roe": "",
    "promoter_holding": "",
    "sales_growth_3y": "",
    "mkt_cap": "",
    "cmp": ""
  },
  {
    "name": "Anant Raj",
    "path": "/company/ANANTRAJ/consolidated/",
    "slug": "ANANTRAJ",
    "ev_ebitda": "",
    "pe": "",
    "pb": "",
    "roce": "",
    "roe": "",
    "promoter_holding": "",
    "sales_growth_3y": "",
    "mkt_cap": "",
    "cmp": ""
  },
  {
    "name": "Aadhar Hsg. Fin.",
    "path": "/company/AADHARHFC/consolidated/",
    "slug": "AADHARHFC",
    "ev_ebitda": "",
    "pe": "",
    "pb": "",
    "roce": "",
    "roe": "",
    "promoter_holding": "",
    "sales_growth_3y": "",
    "mkt_cap": "",
    "cmp": ""
  },
  {
    "name": "Sun TV Network",
    "path": "/company/SUNTV/consolidated/",
    "slug": "SUNTV",
    "ev_ebitda": "",
    "pe": "",
    "pb": "",
    "roce": "",
    "roe": "",
    "promoter_holding": "",
    "sales_growth_3y": "",
    "mkt_cap": "",
    "cmp": ""
  },
  {
    "name": "Pfizer",
    "path": "/company/PFIZER/",
    "slug": "PFIZER",
    "ev_ebitda": "",
    "pe": "",
    "pb": "",
    "roce": "",
    "roe": "",
    "promoter_holding": "",
    "sales_growth_3y": "",
    "mkt_cap": "",
    "cmp": ""
  },
  {
    "name": "CreditAcc. Gram.",
    "path": "/company/CREDITACC/",
    "slug": "CREDITACC",
    "ev_ebitda": "",
    "pe": "",
    "pb": "",
    "roce": "",
    "roe": "",
    "promoter_holding": "",
    "sales_growth_3y": "",
    "mkt_cap": "",
    "cmp": ""
  },
  {
    "name": "Hatsun Agro",
    "path": "/company/HATSUN/",
    "slug": "HATSUN",
    "ev_ebitda": "",
    "pe": "",
    "pb": "",
    "roce": "",
    "roe": "",
    "promoter_holding": "",
    "sales_growth_3y": "",
    "mkt_cap": "",
    "cmp": ""
  },
  {
    "name": "Cube Highways",
    "path": "/company/CUBEINVIT/consolidated/",
    "slug": "CUBEINVIT",
    "ev_ebitda": "",
    "pe": "",
    "pb": "",
    "roce": "",
    "roe": "",
    "promoter_holding": "",
    "sales_growth_3y": "",
    "mkt_cap": "",
    "cmp": ""
  },
  {
    "name": "Rubicon Research",
    "path": "/company/RUBICON/consolidated/",
    "slug": "RUBICON",
    "ev_ebitda": "",
    "pe": "",
    "pb": "",
    "roce": "",
    "roe": "",
    "promoter_holding": "",
    "sales_growth_3y": "",
    "mkt_cap": "",
    "cmp": ""
  },
  {
    "name": "Carborundum Uni.",
    "path": "/company/CARBORUNIV/consolidated/",
    "slug": "CARBORUNIV",
    "ev_ebitda": "",
    "pe": "",
    "pb": "",
    "roce": "",
    "roe": "",
    "promoter_holding": "",
    "sales_growth_3y": "",
    "mkt_cap": "",
    "cmp": ""
  },
  {
    "name": "Ola Electric",
    "path": "/company/OLAELEC/consolidated/",
    "slug": "OLAELEC",
    "ev_ebitda": "",
    "pe": "",
    "pb": "",
    "roce": "",
    "roe": "",
    "promoter_holding": "",
    "sales_growth_3y": "",
    "mkt_cap": "",
    "cmp": ""
  },
  {
    "name": "Atul",
    "path": "/company/ATUL/consolidated/",
    "slug": "ATUL",
    "ev_ebitda": "",
    "pe": "",
    "pb": "",
    "roce": "",
    "roe": "",
    "promoter_holding": "",
    "sales_growth_3y": "",
    "mkt_cap": "",
    "cmp": ""
  },
  {
    "name": "Granules India",
    "path": "/company/GRANULES/consolidated/",
    "slug": "GRANULES",
    "ev_ebitda": "",
    "pe": "",
    "pb": "",
    "roce": "",
    "roe": "",
    "promoter_holding": "",
    "sales_growth_3y": "",
    "mkt_cap": "",
    "cmp": ""
  }
]
